{"nome": "eda",
                    "aulas" : [
                        {
                            "data": "26/09/2022",
                            "creditos": "2",
                            "assunto": "Introdução ao curso e Introdução à análise de algoritmos"
                        },
                        {
                            "data": "29/09/2022",
                            "creditos": "2",
                            "assunto": "Introdução à análise de algoritmos"
                        },
                        {
                            "data": "03/10/2022",
                            "creditos": "2",
                            "assunto": "Análise assintótica: visão geral"
                        },
                        {
                            "data": "06/10/2022",
                            "creditos": "2",
                            "assunto": "Análise assintótica: notações"
                        },
                        {
                            "data": "10/10/2022",
                            "creditos": "2",
                            "assunto": "Análise de algoritmos recursivos"
                        },
                        {
                            "data": "13/10/2022",
                            "creditos": "2",
                            "assunto": "Análise de algoritmos recursivos"
                        },
                        {
                            "data": "17/10/2022",
                            "creditos": "2",
                            "assunto": "Bubblesort, selectionsort e insertionsort"
                        },
                        {
                            "data": "20/10/2022",
                            "creditos": "2",
                            "assunto": "Bubblesort, selectionsort e insertionsort"
                        },
                        {
                            "data": "24/10/2022",
                            "creditos": "2",
                            "assunto": "Mergesort e quicksort"
                        },
                        {
                            "data": "27/10/2022",
                            "creditos": "2",
                            "assunto": "Mergesort e quicksort"
                        },
                        {
                            "data": "31/10/2022",
                            "creditos": "2",
                            "assunto": "Countingsort e radixsort"
                        },
                        {
                            "data": "03/11/2022",
                            "creditos": "2",
                            "assunto": "Countingsort e radixsort"
                        },
                        {
                            "data": "07/11/2022",
                            "creditos": "2",
                            "assunto": "Avaliação de Primeiro Estágio"
                        },
                        {
                            "data": "10/11/2022",
                            "creditos": "2",
                            "assunto": "EDs baseadas em arrays"
                        },
                        {
                            "data": "14/11/2022",
                            "creditos": "2",
                            "assunto": "EDs baseadas em arrays"
                        },
                        {
                            "data": "17/11/2022",
                            "creditos": "2",
                            "assunto": "LinkedList: abordagem iterativa"
                        },
                        {
                            "data": "21/11/2022",
                            "creditos": "2",
                            "assunto": "LinkedList: abordagem recursivo"
                        },
                        {
                            "data": "24/11/2022",
                            "creditos": "2",
                            "assunto": "Tabelas Hash: endereçamento fechado"
                        },
                        {
                            "data": "28/11/2022",
                            "creditos": "2",
                            "assunto": "Tabelas Hash: endereçamento aberto"
                        },
                        {
                            "data": "01/12/2022",
                            "creditos": "2",
                            "assunto": "Avaliação de Segundo Estágio"
                        },
                        {
                            "data": "05/12/2022",
                            "creditos": "2",
                            "assunto": "Árvores Binárias de Pesquisa: conceitos"
                        },
                        {
                            "data": "08/12/2022",
                            "creditos": "2",
                            "assunto": "Árvores Binárias de Pesquisa: operações"
                        },
                        {
                            "data": "12/12/2022",
                            "creditos": "2",
                            "assunto": "Árvores Binárias de Pesquisa: operações"
                        },
                        {
                            "data": "15/12/2022",
                            "creditos": "2",
                            "assunto": "Heap: operações básicas"
                        },
                        {
                            "data": "19/12/2022",
                            "creditos": "2",
                            "assunto": "Heap: buildheap e heapsort"
                        },
                        {
                            "data": "22/12/2022",
                            "creditos": "2",
                            "assunto": "Balanceamento: rotações"
                        },
                        {
                            "data": "02/02/2023",
                            "creditos": "2",
                            "assunto": "AVL: operação de inserção"
                        },
                        {
                            "data": "06/02/2023",
                            "creditos": "2",
                            "assunto": "Árvores PV e  Árvores B"
                        },
                        {
                            "data": "09/02/2023",
                            "creditos": "2",
                            "assunto": "Avaliação de Terceiro Estágio"
                        },
                        {
                            "data": "13/02/2023",
                            "creditos": "2",
                            "assunto": "Avaliação de Reposição"
                        },
                        {
                            "data": "16/02/2023",
                            "creditos": "2",
                            "assunto": "Avaliação: Prova Final"
                        }
                    ],
                    "codigo": "1411305",
                    "plano" : {"ementa": "Complexidade de algoritmos. Estruturas de dados básicas e avançadas. Algoritmos de ordenação: por comparação e divisão e conquista e algoritmos em tempo linear. Tabelas hash. Hash dinamico. Pesquisa em árvores binárias. Árvores balanceadas. Heap Binária. Árvores P-V. árvores Splay. Skip List. Árvore B. Algoritmos sobre grafos. Ordenação. Estruturas indexadas para armazenamento em memória secundária.",         
                               "objetivos": "Compreender a análise de complexidade de tempo de algoritmos. Escolher algoritmos baseando-se em seu tempo de execução. Entender os principais métodos de ordenação . Compreender e usar as estruturas de dados básicas e avançadas e seus algoritmos.",
                               "conteudo": "Análise de algoritmos: notação assintótica, método iterativo e método mestre. Algoritmos de ordenação: Bubble sort, Selection Sort, Insertion Sort, Shell Sort, Merge Sort, Quick Sort. Tipo Abstrato de Dados. Vetor, Pilha e Lista. Árvores binárias. Heap binária. Árvores AVL, PV. e B. Skip List. Árvores Splay. Algoritmos sobre grafos.",
                               "metodologia": "Aulas expositivas e aulas de exercícios.",
                               "avaliacao": "Mini-testes, Prova e Atividades Extras.",
                               "referencias": "CORMEN, T. H. et.al. Algoritmos: teoria e prática, 3 edição. Ed. Campus, 2002. Site do autor: http://mitpress.mit.edu/algorithms/ \n SEDGEWICK, Robert; WAYNE, Kevin. Algorithms. Addison-wesley professional, 2011."
                              }
           }
